timefiller/__init__.py
timefiller/_estimator.py
timefiller/_misc.py
timefiller/_multivariate_imputer.py
timefiller/_positive_output_transformer.py
timefiller/_time_series_imputer.py
timefiller/utils/__init__.py
timefiller/utils/_datasets.py
timefiller/utils/_random_time_series.py
timefiller-1.0.6.dist-info/LICENSE
timefiller-1.0.6.dist-info/METADATA
timefiller-1.0.6.dist-info/WHEEL
timefiller-1.0.6.dist-info/top_level.txt
timefiller-1.0.6.dist-info/RECORD
