Metadata-Version: 2.2
Name: timefiller
Version: 1.0.6
Summary: A package for imputing missing data in time series and forecasting in missing-data contexts
Author: Cyril Joly
Project-URL: Homepage, https://github.com/CyrilJl/TimeFiller
Classifier: License :: OSI Approved :: MIT License
Requires-Python: >=3.8
License-File: LICENSE
Requires-Dist: mapie
Requires-Dist: numpy
Requires-Dist: optimask
Requires-Dist: pandas
Requires-Dist: scikit-learn
Requires-Dist: tqdm
Provides-Extra: test
Requires-Dist: pytest; extra == "test"
Requires-Dist: requests; extra == "test"
